Asthowen/__init__.py
Asthowen-0.0.0.dist-info/METADATA
Asthowen-0.0.0.dist-info/WHEEL
Asthowen-0.0.0.dist-info/top_level.txt
Asthowen-0.0.0.dist-info/RECORD
