Metadata-Version: 2.1
Name: Asthowen
Version: 0.0.0
Summary: The Python wrapper for the Asthowen API
Home-page: https://github.com/Asthowen/AsthowenAPI
Author: Asthowen
License: UNKNOWN
Platform: UNKNOWN
Requires-Python: >= 3.6
